piprequester/__init__.py
piprequester-1.0.0.dist-info/METADATA
piprequester-1.0.0.dist-info/WHEEL
piprequester-1.0.0.dist-info/top_level.txt
piprequester-1.0.0.dist-info/RECORD
