Metadata-Version: 2.1
Name: piprequester
Version: 1.0.0
Summary: A Python package to handle requests via HTTP in Python. HTTPS is also Supported
Home-page: UNKNOWN
Author: ЕntchenBuilds
Author-email: ЕntchenBuilds@gmail.com
License: UNKNOWN
Keywords: python
Platform: UNKNOWN
Classifier: Operating System :: Microsoft :: Windows
